Metadata-Version: 1.1
Name: starspot
Version: 0.1
Summary: Tools for measuring stellar rotation periods
Home-page: http://github.com/RuthAngus/starspot
Author: Ruth Angus
Author-email: ruthangus@gmail.com
License: MIT
Download-URL: https://github.com/RuthAngus/starspot/archive/v0.1.tar.gz
Platform: UNKNOWN
